zos_ftp_mcp/__init__.py
zos_ftp_mcp/exceptions.py
zos_ftp_mcp/models.py
zos_ftp_mcp/server.py
zos_ftp_mcp/zos_ftp.py
zos_ftp_mcp-0.1.3.dist-info/licenses/LICENSE
zos_ftp_mcp-0.1.3.dist-info/METADATA
zos_ftp_mcp-0.1.3.dist-info/WHEEL
zos_ftp_mcp-0.1.3.dist-info/entry_points.txt
zos_ftp_mcp-0.1.3.dist-info/top_level.txt
zos_ftp_mcp-0.1.3.dist-info/RECORD
