Metadata-Version: 2.4
Name: zos-ftp-mcp
Version: 0.1.3
Summary: MCP server for z/OS mainframe FTP operations
Author-email: Arunkumar Selvam <aruninfy123@gmail.com>
License: MIT
Project-URL: Homepage, https://github.com/arunkumars-mf/zos-ftp-mcp
Project-URL: Bug Reports, https://github.com/arunkumars-mf/zos-ftp-mcp/issues
Project-URL: Source, https://github.com/arunkumars-mf/zos-ftp-mcp
Keywords: mainframe,zos,ftp,mcp,dataset,pds
Classifier: Development Status :: 3 - Alpha
Classifier: Intended Audience :: Developers
Classifier: Topic :: Software Development :: Libraries :: Python Modules
Classifier: Topic :: System :: Systems Administration
Classifier: Programming Language :: Python :: 3
Classifier: Programming Language :: Python :: 3.10
Classifier: Programming Language :: Python :: 3.11
Classifier: Programming Language :: Python :: 3.12
Classifier: Programming Language :: Python :: 3.13
Classifier: License :: OSI Approved :: MIT License
Classifier: Operating System :: OS Independent
Requires-Python: >=3.10
License-File: LICENSE
Requires-Dist: mcp>=1.0.0
Dynamic: license-file
